ovs/__init__.py
ovs/daemon.py
ovs/dirs.py
ovs/fatal_signal.py
ovs/fcntl_win.py
ovs/json.py
ovs/jsonrpc.py
ovs/ovsuuid.py
ovs/poller.py
ovs/process.py
ovs/reconnect.py
ovs/socket_util.py
ovs/stream.py
ovs/timeval.py
ovs/util.py
ovs/version.py
ovs/vlog.py
ovs/winutils.py
ovs/compat/__init__.py
ovs/compat/sortedcontainers/__init__.py
ovs/compat/sortedcontainers/sorteddict.py
ovs/compat/sortedcontainers/sortedlist.py
ovs/compat/sortedcontainers/sortedset.py
ovs/db/__init__.py
ovs/db/custom_index.py
ovs/db/data.py
ovs/db/error.py
ovs/db/idl.py
ovs/db/parser.py
ovs/db/schema.py
ovs/db/types.py
ovs/unixctl/__init__.py
ovs/unixctl/client.py
ovs/unixctl/server.py
ovs-2.17.1.post1.dist-info/METADATA
ovs-2.17.1.post1.dist-info/WHEEL
ovs-2.17.1.post1.dist-info/top_level.txt
ovs-2.17.1.post1.dist-info/RECORD
