Metadata-Version: 2.1
Name: ovs
Version: 2.17.1.post1
Summary: Open vSwitch library
Home-page: http://www.openvswitch.org/
Author: Open vSwitch
Author-email: dev@openvswitch.org
License: Apache 2.0
Keywords: openvswitch,ovs,OVSDB
Platform: UNKNOWN
Classifier: Development Status :: 5 - Production/Stable
Classifier: Topic :: Database :: Front-Ends
Classifier: Topic :: Software Development :: Libraries :: Python Modules
Classifier: Topic :: System :: Networking
Classifier: License :: OSI Approved :: Apache Software License
Classifier: Programming Language :: Python :: 3
Classifier: Programming Language :: Python :: 3.4
Classifier: Programming Language :: Python :: 3.5
